vantaether/__init__.py
vantaether/__main__.py
vantaether/config.py
vantaether/exceptions.py
vantaether/assets/tampermonkey_script.js
vantaether/core/__init__.py
vantaether/core/analyzer.py
vantaether/core/downloader.py
vantaether/core/engine.py
vantaether/core/merger.py
vantaether/core/native.py
vantaether/core/playlist.py
vantaether/core/selector.py
vantaether/core/subtitle_processor.py
vantaether/locales/en.json
vantaether/locales/tr.json
vantaether/server/__init__.py
vantaether/server/app.py
vantaether/server/templates.py
vantaether/utils/__init__.py
vantaether/utils/cookies.py
vantaether/utils/file_manager.py
vantaether/utils/header_factory.py
vantaether/utils/i18n.py
vantaether/utils/report_generator.py
vantaether/utils/system.py
vantaether/utils/ui.py
vantaether-2.2.0.dist-info/licenses/LICENSE
vantaether-2.2.0.dist-info/METADATA
vantaether-2.2.0.dist-info/WHEEL
vantaether-2.2.0.dist-info/entry_points.txt
vantaether-2.2.0.dist-info/top_level.txt
vantaether-2.2.0.dist-info/RECORD
