Metadata-Version: 2.4
Name: VantaEther
Version: 2.2.0
Summary: VantaEther is an advanced media stream sniffer, analyzer, and downloader.
Author-email: ciwga <vantaether@tutanota.com>
License: MIT License
Project-URL: Homepage, https://github.com/ciwga/VantaEther
Project-URL: Issues, https://github.com/ciwga/VantaEther/issues
Classifier: Programming Language :: Python :: 3
Classifier: License :: OSI Approved :: MIT License
Classifier: Operating System :: OS Independent
Classifier: Environment :: Console
Classifier: Framework :: Flask
Classifier: Topic :: Multimedia :: Video
Classifier: Topic :: Internet :: WWW/HTTP :: Dynamic Content
Requires-Python: >=3.8
License-File: LICENSE
Requires-Dist: requests
Requires-Dist: yt-dlp
Requires-Dist: flask
Requires-Dist: rich
Dynamic: license-file
